[
  {
    "name": "Black & White",
    "preview1": "https://i.imgur.com/iWyPTlo.jpg",
    "preview2": "https://images.unsplash.com/photo-1493928841026-e1ab0a590a61?ixlib=rb-1.2.1&ixid=eyJhcHBfaWQiOjEyMDd9&auto=format&fit=crop&w=500&q=60",
    "preview3": "https://images.unsplash.com/photo-1581388847562-d5a56eec1cfb?ixlib=rb-1.2.1&ixid=eyJhcHBfaWQiOjEyMDd9&auto=format&fit=crop&w=500&q=60"
  },
  {
    "name": "Animals",
    "preview1": "https://images.unsplash.com/photo-1574870111867-089730e5a72b?ixlib=rb-1.2.1&ixid=eyJhcHBfaWQiOjEyMDd9&auto=format&fit=crop&w=500&q=60",
    "preview2": "https://i.imgur.com/iWyPTlo.jpg",
    "preview3": "https://images.unsplash.com/photo-1516934024742-b461fba47600?ixlib=rb-1.2.1&ixid=eyJhcHBfaWQiOjEyMDd9&auto=format&fit=crop&w=500&q=60"
  },
  {
    "name": "Painting",
    "preview1": "https://images.unsplash.com/photo-1579783901586-d88db74b4fe4?ixlib=rb-1.2.1&ixid=eyJhcHBfaWQiOjEyMDd9&auto=format&fit=crop&w=500&q=60",
    "preview2": "https://i.imgur.com/zFu1Fyx.jpg",
    "preview3": "https://images.unsplash.com/photo-1553949345-eb786bb3f7ba?ixlib=rb-1.2.1&ixid=eyJhcHBfaWQiOjEyMDd9&auto=format&fit=crop&w=500&q=60"
  },
  {
    "name": "Scenery",
    "preview1": "https://images.unsplash.com/photo-1500322969630-a26ab6eb64cc?ixlib=rb-1.2.1&ixid=eyJhcHBfaWQiOjEyMDd9&auto=format&fit=crop&w=500&q=60",
    "preview2": "https://images.unsplash.com/photo-1491466424936-e304919aada7?ixlib=rb-1.2.1&ixid=eyJhcHBfaWQiOjEyMDd9&auto=format&fit=crop&w=500&q=60",
    "preview3": "https://images.unsplash.com/photo-1521747116042-5a810fda9664?ixlib=rb-1.2.1&ixid=eyJhcHBfaWQiOjEyMDd9&auto=format&fit=crop&w=500&q=60"
  },
  {
    "name": "Architecture",
    "preview1": "https://picsum.photos/id/197/427/284",
    "preview2": "https://images.unsplash.com/photo-1541272017511-17bc201c523f?ixlib=rb-1.2.1&ixid=eyJhcHBfaWQiOjEyMDd9&auto=format&fit=crop&w=500&q=60",
    "preview3": "https://picsum.photos/id/195/200/200"
  },
  {
    "name": "Person",
    "preview1": "https://images.unsplash.com/photo-1494959764136-6be9eb3c261e?ixlib=rb-1.2.1&ixid=eyJhcHBfaWQiOjEyMDd9&auto=format&fit=crop&w=500&q=60",
    "preview2": "https://images.unsplash.com/photo-1503249023995-51b0f3778ccf?ixlib=rb-1.2.1&ixid=eyJhcHBfaWQiOjEyMDd9&auto=format&fit=crop&w=500&q=60",
    "preview3": "https://picsum.photos/id/203/427/284"
  },
  {
    "name": "Lights",
    "preview1": "https://images.unsplash.com/photo-1507494924047-60b8ee826ca9?ixlib=rb-1.2.1&ixid=eyJhcHBfaWQiOjEyMDd9&auto=format&fit=crop&w=500&q=60",
    "preview2": "https://images.unsplash.com/photo-1515245696852-ae418cad9b62?ixlib=rb-1.2.1&ixid=eyJhcHBfaWQiOjEyMDd9&auto=format&fit=crop&w=500&q=60",
    "preview3": "https://picsum.photos/id/195/768/1024"
  },
  {
    "name": "Wood",
    "preview1": "https://images.unsplash.com/photo-1515446134809-993c501ca304?ixlib=rb-1.2.1&ixid=eyJhcHBfaWQiOjEyMDd9&auto=format&fit=crop&w=500&q=60",
    "preview2": "https://images.unsplash.com/photo-1571205086863-9d186c5cb8fb?ixlib=rb-1.2.1&ixid=eyJhcHBfaWQiOjEyMDd9&auto=format&fit=crop&w=500&q=60",
    "preview3": "https://images.unsplash.com/photo-1517958189574-a9423e47b514?ixlib=rb-1.2.1&ixid=eyJhcHBfaWQiOjEyMDd9&auto=format&fit=crop&w=500&q=60"
  },
  {
    "name": "Technology",
    "preview1": "https://images.unsplash.com/photo-1593642702749-b7d2a804fbcf?ixlib=rb-1.2.1&ixid=eyJhcHBfaWQiOjEyMDd9&auto=format&fit=crop&w=500&q=60",
    "preview2": "https://picsum.photos/id/201/427/284",
    "preview3": "https://images.unsplash.com/photo-1518770660439-4636190af475?ixlib=rb-1.2.1&ixid=eyJhcHBfaWQiOjEyMDd9&auto=format&fit=crop&w=500&q=60"
  }
]